felmateos/__init__.py
felmateos/my_functions.py
felmateos-0.1.2.dist-info/METADATA
felmateos-0.1.2.dist-info/WHEEL
felmateos-0.1.2.dist-info/top_level.txt
felmateos-0.1.2.dist-info/RECORD
