Metadata-Version: 2.1
Name: felmateos
Version: 0.1.2
Summary: My first Python library
Author: Me
